{
  "source_id": "SRC-0001",
  "title": "Th\u00e8me2",
  "max_words": 1200,
  "overlap_words": 150,
  "chunk_count": 10,
  "date_chunked": "2026-06-04T02:25:26-04:00",
  "chunks": [
    {
      "chunk_id": "SRC-0001-CHUNK-0001",
      "chunk_number": 1,
      "file_path": "C:\\StudyForge\\courses\\ECA1010_Microeconomics\\02_Extracted_Text\\chunks\\SRC-0001\\SRC-0001-CHUNK-0001.md",
      "page_start": 1,
      "page_end": 21,
      "pages": [
        1,
        2,
        3,
        4,
        5,
        6,
        7,
        8,
        9,
        10,
        12,
        13,
        14,
        15,
        16,
        17,
        18,
        19,
        20,
        21
      ],
      "word_count": 1255
    },
    {
      "chunk_id": "SRC-0001-CHUNK-0002",
      "chunk_number": 2,
      "file_path": "C:\\StudyForge\\courses\\ECA1010_Microeconomics\\02_Extracted_Text\\chunks\\SRC-0001\\SRC-0001-CHUNK-0002.md",
      "page_start": 1,
      "page_end": 26,
      "pages": [
        1,
        2,
        3,
        4,
        5,
        6,
        7,
        8,
        9,
        10,
        12,
        13,
        14,
        15,
        16,
        17,
        18,
        19,
        20,
        21,
        22,
        23,
        24,
        25,
        26
      ],
      "word_count": 1188
    },
    {
      "chunk_id": "SRC-0001-CHUNK-0003",
      "chunk_number": 3,
      "file_path": "C:\\StudyForge\\courses\\ECA1010_Microeconomics\\02_Extracted_Text\\chunks\\SRC-0001\\SRC-0001-CHUNK-0003.md",
      "page_start": 1,
      "page_end": 27,
      "pages": [
        1,
        2,
        3,
        4,
        5,
        6,
        7,
        8,
        9,
        10,
        12,
        13,
        14,
        15,
        16,
        17,
        18,
        19,
        20,
        21,
        22,
        23,
        24,
        25,
        26,
        27
      ],
      "word_count": 772
    },
    {
      "chunk_id": "SRC-0001-CHUNK-0004",
      "chunk_number": 4,
      "file_path": "C:\\StudyForge\\courses\\ECA1010_Microeconomics\\02_Extracted_Text\\chunks\\SRC-0001\\SRC-0001-CHUNK-0004.md",
      "page_start": 1,
      "page_end": 29,
      "pages": [
        1,
        2,
        3,
        4,
        5,
        6,
        7,
        8,
        9,
        10,
        12,
        13,
        14,
        15,
        16,
        17,
        18,
        19,
        20,
        21,
        22,
        23,
        24,
        25,
        26,
        27,
        28,
        29
      ],
      "word_count": 1001
    },
    {
      "chunk_id": "SRC-0001-CHUNK-0005",
      "chunk_number": 5,
      "file_path": "C:\\StudyForge\\courses\\ECA1010_Microeconomics\\02_Extracted_Text\\chunks\\SRC-0001\\SRC-0001-CHUNK-0005.md",
      "page_start": 1,
      "page_end": 35,
      "pages": [
        1,
        2,
        3,
        4,
        5,
        6,
        7,
        8,
        9,
        10,
        12,
        13,
        14,
        15,
        16,
        17,
        18,
        19,
        20,
        21,
        22,
        23,
        24,
        25,
        26,
        27,
        28,
        29,
        30,
        31,
        32,
        33,
        34,
        35
      ],
      "word_count": 1071
    },
    {
      "chunk_id": "SRC-0001-CHUNK-0006",
      "chunk_number": 6,
      "file_path": "C:\\StudyForge\\courses\\ECA1010_Microeconomics\\02_Extracted_Text\\chunks\\SRC-0001\\SRC-0001-CHUNK-0006.md",
      "page_start": 1,
      "page_end": 39,
      "pages": [
        1,
        2,
        3,
        4,
        5,
        6,
        7,
        8,
        9,
        10,
        12,
        13,
        14,
        15,
        16,
        17,
        18,
        19,
        20,
        21,
        22,
        23,
        24,
        25,
        26,
        27,
        28,
        29,
        30,
        31,
        32,
        33,
        34,
        35,
        36,
        37,
        38,
        39
      ],
      "word_count": 1196
    },
    {
      "chunk_id": "SRC-0001-CHUNK-0007",
      "chunk_number": 7,
      "file_path": "C:\\StudyForge\\courses\\ECA1010_Microeconomics\\02_Extracted_Text\\chunks\\SRC-0001\\SRC-0001-CHUNK-0007.md",
      "page_start": 1,
      "page_end": 41,
      "pages": [
        1,
        2,
        3,
        4,
        5,
        6,
        7,
        8,
        9,
        10,
        12,
        13,
        14,
        15,
        16,
        17,
        18,
        19,
        20,
        21,
        22,
        23,
        24,
        25,
        26,
        27,
        28,
        29,
        30,
        31,
        32,
        33,
        34,
        35,
        36,
        37,
        38,
        39,
        40,
        41
      ],
      "word_count": 1061
    },
    {
      "chunk_id": "SRC-0001-CHUNK-0008",
      "chunk_number": 8,
      "file_path": "C:\\StudyForge\\courses\\ECA1010_Microeconomics\\02_Extracted_Text\\chunks\\SRC-0001\\SRC-0001-CHUNK-0008.md",
      "page_start": 1,
      "page_end": 42,
      "pages": [
        1,
        2,
        3,
        4,
        5,
        6,
        7,
        8,
        9,
        10,
        12,
        13,
        14,
        15,
        16,
        17,
        18,
        19,
        20,
        21,
        22,
        23,
        24,
        25,
        26,
        27,
        28,
        29,
        30,
        31,
        32,
        33,
        34,
        35,
        36,
        37,
        38,
        39,
        40,
        41,
        42
      ],
      "word_count": 772
    },
    {
      "chunk_id": "SRC-0001-CHUNK-0009",
      "chunk_number": 9,
      "file_path": "C:\\StudyForge\\courses\\ECA1010_Microeconomics\\02_Extracted_Text\\chunks\\SRC-0001\\SRC-0001-CHUNK-0009.md",
      "page_start": 1,
      "page_end": 44,
      "pages": [
        1,
        2,
        3,
        4,
        5,
        6,
        7,
        8,
        9,
        10,
        12,
        13,
        14,
        15,
        16,
        17,
        18,
        19,
        20,
        21,
        22,
        23,
        24,
        25,
        26,
        27,
        28,
        29,
        30,
        31,
        32,
        33,
        34,
        35,
        36,
        37,
        38,
        39,
        40,
        41,
        42,
        43,
        44
      ],
      "word_count": 1001
    },
    {
      "chunk_id": "SRC-0001-CHUNK-0010",
      "chunk_number": 10,
      "file_path": "C:\\StudyForge\\courses\\ECA1010_Microeconomics\\02_Extracted_Text\\chunks\\SRC-0001\\SRC-0001-CHUNK-0010.md",
      "page_start": 1,
      "page_end": 46,
      "pages": [
        1,
        2,
        3,
        4,
        5,
        6,
        7,
        8,
        9,
        10,
        12,
        13,
        14,
        15,
        16,
        17,
        18,
        19,
        20,
        21,
        22,
        23,
        24,
        25,
        26,
        27,
        28,
        29,
        30,
        31,
        32,
        33,
        34,
        35,
        36,
        37,
        38,
        39,
        40,
        41,
        42,
        43,
        44,
        45,
        46
      ],
      "word_count": 450
    }
  ],
  "warnings": []
}
